trytond/modules/jinja_report/__init__.py
trytond/modules/jinja_report/report.py
trytond/modules/jinja_report/tryton.cfg
trytond/modules/jinja_report/tests/__init__.py
trytond/modules/jinja_report/tests/test_jinja_report.py
trytoncalidae_jinja_report-7.2.1.dist-info/LICENSE
trytoncalidae_jinja_report-7.2.1.dist-info/METADATA
trytoncalidae_jinja_report-7.2.1.dist-info/WHEEL
trytoncalidae_jinja_report-7.2.1.dist-info/entry_points.txt
trytoncalidae_jinja_report-7.2.1.dist-info/top_level.txt
trytoncalidae_jinja_report-7.2.1.dist-info/RECORD
