Metadata-Version: 2.1
Name: trytoncalidae_jinja_report
Version: 7.2.1
Summary: Create Tryton reports based on jinja2 python library
Home-page: https://github.com/calidae/
Download-URL: https://github.com/calidae/jinja_report
Author: Calidae
Author-email: dev@calidae.com
License: GPL-3
Classifier: Development Status :: 5 - Production/Stable
Classifier: Environment :: Plugins
Classifier: Framework :: Tryton
Classifier: Intended Audience :: Developers
Classifier: Intended Audience :: Financial and Insurance Industry
Classifier: Intended Audience :: Legal Industry
Classifier: License :: OSI Approved :: GNU General Public License (GPL)
Classifier: Natural Language :: Catalan
Classifier: Natural Language :: English
Classifier: Natural Language :: Spanish
Classifier: Operating System :: OS Independent
Classifier: Programming Language :: Python :: 3.8
Classifier: Programming Language :: Python :: 3.9
Classifier: Programming Language :: Python :: 3.10
Classifier: Programming Language :: Python :: 3.11
Classifier: Programming Language :: Python :: 3.12
Classifier: Topic :: Office/Business
License-File: LICENSE
Requires-Dist: jinja2
Requires-Dist: trytond <7.3,>=7.2
Provides-Extra: dev
Requires-Dist: trytond-factories <7.3,>=7.2 ; extra == 'dev'
